adventuresinodyssey/__init__.py
adventuresinodyssey/aioclient.py
adventuresinodyssey/clubclient.py
adventuresinodyssey-0.1.8.dist-info/METADATA
adventuresinodyssey-0.1.8.dist-info/WHEEL
adventuresinodyssey-0.1.8.dist-info/top_level.txt
adventuresinodyssey-0.1.8.dist-info/RECORD
