Metadata-Version: 2.4
Name: adventuresinodyssey
Version: 0.1.8
Summary: Python API clients for Adventures in Odyssey.
Author-email: CATEIN <CATEIN@protonmail.com>
License-Expression: MIT
Project-URL: Homepage, https://github.com/CATEIN/adventuresinodyssey-py
Project-URL: Repository, https://github.com/CATEIN/adventuresinodyssey-py
Classifier: Development Status :: 3 - Alpha
Classifier: Intended Audience :: Developers
Classifier: Programming Language :: Python :: 3
Classifier: Topic :: Internet :: WWW/HTTP
Requires-Python: >=3.8
Requires-Dist: requests>=2.28.1
Requires-Dist: playwright>=1.40.0
